{
    "book": "यशायाह अध्याय",
    "chapter": 20,
    "verses": [
        {
            "verse": 1,
            "text": [
                "उस वर्ष जब सेनापति अशदोद आया, जब अश्शूर के राजा सरगोन ने उसे भेजा और उसने अशदोद के विरुद्ध युद्ध किया और उसे जीत लिया,"
            ]
        },
        {
            "verse": 2,
            "text": [
                "उसी समय यहोवा ने आमोज के पुत्र यशायाह के द्वारा कहा, “जाओ और अपनी कमर से टाट का वस्त्र उतार दो, और अपने पैरों से जूते उतार दो।” और उसने ऐसा ही किया, नग्न और नंगे पैर चलने लगा।"
            ]
        },
        {
            "verse": 3,
            "text": [
                "तब यहोवा ने कहा, “जैसे मेरे सेवक यशायाह ने तीन वर्षों तक मिस्र और कूश के विरुद्ध एक चिन्ह और चेतावनी के रूप में नग्न और नंगे पैर चलकर दिखाया है,"
            ]
        },
        {
            "verse": 4,
            "text": [
                "वैसे ही अश्शूर का राजा मिस्र के बंदियों और कूश के निर्वासितों को, जवान और बूढ़े, नग्न और नंगे पैर, बिना ढके नितंबों के साथ ले जाएगा, मिस्र की लज्जा के लिए।"
            ]
        },
        {
            "verse": 5,
            "text": [
                "तब वे कूश पर अपनी आशा और मिस्र पर अपने गर्व के कारण लज्जित होंगे।"
            ]
        },
        {
            "verse": 6,
            "text": [
                "इसलिए इस तटवर्ती प्रदेश के निवासी उस दिन कहेंगे, ‘देखो, यही हमारी आशा है, जहाँ हम अश्शूर के राजा से बचने के लिए सहायता के लिए भागे थे; और हम स्वयं कैसे बच सकते हैं?’”"
            ]
        }
    ]
}